gpt_all_star/__init__.py
gpt_all_star/agents.yml
gpt_all_star/cli/__init__.py
gpt_all_star/cli/console_terminal.py
gpt_all_star/core/__init__.py
gpt_all_star/core/agents/__init__.py
gpt_all_star/core/agents/agent.py
gpt_all_star/core/agents/agent_state.py
gpt_all_star/core/agents/agents.py
gpt_all_star/core/agents/architect.py
gpt_all_star/core/agents/chain.py
gpt_all_star/core/agents/copilot.py
gpt_all_star/core/agents/designer.py
gpt_all_star/core/agents/engineer.py
gpt_all_star/core/agents/product_owner.py
gpt_all_star/core/agents/project_manager.py
gpt_all_star/core/agents/qa_engineer.py
gpt_all_star/core/deployment/__init__.py
gpt_all_star/core/deployment/deployment.py
gpt_all_star/core/execution/__init__.py
gpt_all_star/core/execution/execution.py
gpt_all_star/core/implement_prompt.py
gpt_all_star/core/message.py
gpt_all_star/core/project.py
gpt_all_star/core/steps/__init__.py
gpt_all_star/core/steps/development/__init__.py
gpt_all_star/core/steps/development/additional_tasks.py
gpt_all_star/core/steps/development/development.py
gpt_all_star/core/steps/development/nodejs_tasks.py
gpt_all_star/core/steps/development/planning_prompt.py
gpt_all_star/core/steps/development/replanning_prompt.py
gpt_all_star/core/steps/entrypoint/__init__.py
gpt_all_star/core/steps/entrypoint/entrypoint.py
gpt_all_star/core/steps/entrypoint/planning_prompt.py
gpt_all_star/core/steps/healing/__init__.py
gpt_all_star/core/steps/healing/healing.py
gpt_all_star/core/steps/healing/planning_prompt.py
gpt_all_star/core/steps/improvement/__init__.py
gpt_all_star/core/steps/improvement/improvement.py
gpt_all_star/core/steps/improvement/planning_prompt.py
gpt_all_star/core/steps/specification/__init__.py
gpt_all_star/core/steps/specification/additional_tasks.py
gpt_all_star/core/steps/specification/specification.py
gpt_all_star/core/steps/step.py
gpt_all_star/core/steps/steps.py
gpt_all_star/core/steps/system_design/__init__.py
gpt_all_star/core/steps/system_design/additional_tasks.py
gpt_all_star-0.0.4.dist-info/LICENSE
gpt_all_star-0.0.4.dist-info/METADATA
gpt_all_star-0.0.4.dist-info/WHEEL
gpt_all_star-0.0.4.dist-info/entry_points.txt
gpt_all_star-0.0.4.dist-info/RECORD
