Metadata-Version: 2.1
Name: gpt-all-star
Version: 0.0.4
Summary: AI-powered code generation tool for scratch development of web applications with a team collaboration of autonomous AI agents. This is a research-project, and its primary value is to explore the possibility of autonomous AI agents.
License: MIT
Author: Yuya Kakui
Author-email: y.kakui@gmail.com
Requires-Python: >=3.10.0,<3.11
Classifier: License :: OSI Approved :: MIT License
Classifier: Programming Language :: Python :: 3
Classifier: Programming Language :: Python :: 3.10
Requires-Dist: gitpython (>=3.1.41,<4.0.0)
Requires-Dist: jinja2 (>=3.1.2,<4.0.0)
Requires-Dist: langchain (>=0.1.0,<0.2.0)
Requires-Dist: langchain-experimental (>=0.0.53,<0.0.54)
Requires-Dist: langchain-openai (>=0.0.8,<0.0.9)
Requires-Dist: langgraph (>=0.0.26,<0.0.27)
Requires-Dist: llama-index (>=0.10.0,<0.11.0)
Requires-Dist: openai (>=1.6.1,<2.0.0)
Requires-Dist: prompt-toolkit (>=3.0.43,<4.0.0)
Requires-Dist: pyfiglet (>=1.0.2,<2.0.0)
Requires-Dist: pygithub (>=2.2.0,<3.0.0)
Requires-Dist: python-dotenv (>=1.0.0,<2.0.0)
Requires-Dist: requests (>=2.31.0,<3.0.0)
Requires-Dist: rich (>=13.7.0,<14.0.0)
Requires-Dist: selenium (>=4.17.2,<5.0.0)
Requires-Dist: termcolor (>=2.4.0,<3.0.0)
Requires-Dist: tiktoken (>=0.5.2,<0.6.0)
Requires-Dist: tree-sitter-languages (>=1.10.2,<2.0.0)
Requires-Dist: typer (>=0.9.0,<0.10.0)
Project-URL: Repository, https://github.com/kyaukyuai/gpt-all-star
